{
  "generated_at": "2026-07-24T12:59:38.642Z",
  "sources": {
    "rotaer_page": "https://aisweb.decea.mil.br/?i=aerodromos&tab=rotaer",
    "rotaer_pdf": "https://aisweb.decea.mil.br/downloads/rotaer/rotaer_completo.pdf",
    "geoserver_wfs": "https://geoaisweb.decea.mil.br/geoserver/ICA/wfs"
  },
  "rotaer": {
    "damdt": "D-AMDT 30-26",
    "effective": "23/07/26",
    "pdfLastModified": "Fri, 24 Jul 2026 12:06:03 GMT",
    "pdfEtag": "\"6a63552b-5ca38f\"",
    "pdfSize": "6071183"
  },
  "layers": {
    "ICA:airport_heliport": {
      "layer": "ICA:airport_heliport",
      "officialCount": 6014,
      "comparableCount": 6014,
      "uniqueCount": 6014,
      "amendment": "2026-07-09Z (6014)",
      "futureAmendment": "-"
    },
    "ICA:waypoint_aisweb": {
      "layer": "ICA:waypoint_aisweb",
      "officialCount": 7938,
      "comparableCount": 7932,
      "uniqueCount": 7932,
      "amendment": "2026-07-09Z (7938)",
      "futureAmendment": "2026-08-06Z (7938)"
    },
    "ICA:vor": {
      "layer": "ICA:vor",
      "officialCount": 77,
      "comparableCount": 77,
      "uniqueCount": null,
      "amendment": "2026-07-09Z (77)",
      "futureAmendment": "2026-08-06Z (77)"
    },
    "ICA:ndb": {
      "layer": "ICA:ndb",
      "officialCount": 24,
      "comparableCount": 24,
      "uniqueCount": null,
      "amendment": "2026-07-09Z (24)",
      "futureAmendment": "2026-08-06Z (24)"
    },
    "ICA:TMA": {
      "layer": "ICA:TMA",
      "officialCount": 62,
      "comparableCount": 62,
      "uniqueCount": null,
      "amendment": "2026-07-09Z (62)",
      "futureAmendment": "2026-08-06Z (62)"
    },
    "ICA:CTR": {
      "layer": "ICA:CTR",
      "officialCount": 65,
      "comparableCount": 65,
      "uniqueCount": null,
      "amendment": "2026-07-09Z (65)",
      "futureAmendment": "2026-08-06Z (65)"
    },
    "ICA:fir": {
      "layer": "ICA:fir",
      "officialCount": 5,
      "comparableCount": 5,
      "uniqueCount": null,
      "amendment": "2026-07-09Z (5)",
      "futureAmendment": "2026-08-06Z (5)"
    }
  }
}
